metalist/__init__.py
metalist/baseclient.py
metalist/client.py
metalist/exceptions.py
metalist.py-1.0.2.dist-info/METADATA
metalist.py-1.0.2.dist-info/RECORD
metalist.py-1.0.2.dist-info/WHEEL
metalist.py-1.0.2.dist-info/top_level.txt
