Metadata-Version: 2.1
Name: metalist.py
Version: 1.0.2
Summary: A simple API wrapper to post Discord bot stats to all known bot lists using metalist.xyz data.
Home-page: https://github.com/MattIPv4/metalist.py/
Author: MattIPv4
License: UNKNOWN
Project-URL: Funding, http://patreon.mattcowley.co.uk/
Project-URL: Support, http://discord.mattcowley.co.uk/
Project-URL: Source, https://github.com/MattIPv4/metalist.py/
Keywords: api wrapper discord bot bots stats statistics meta list metalist botlist
Platform: UNKNOWN
Classifier: License :: OSI Approved :: MIT License
Classifier: Programming Language :: Python :: 3
Classifier: Natural Language :: English
Classifier: Intended Audience :: Developers
Classifier: Operating System :: OS Independent
Requires-Python: >= 3.5
Requires-Dist: aiohttp
